purgpt/__init__.py
PurGPT.py-0.0.1.dist-info/LICENSE
PurGPT.py-0.0.1.dist-info/METADATA
PurGPT.py-0.0.1.dist-info/WHEEL
PurGPT.py-0.0.1.dist-info/top_level.txt
PurGPT.py-0.0.1.dist-info/RECORD
