Metadata-Version: 2.1
Name: PurGPT.py
Version: 0.0.1
Summary: PurGPT.py, the wrapper for the PurGPT API
Author: TheCatsMoo
Author-email: tcm@tcm.gay
Keywords: purgpt,AI
Classifier: Development Status :: 3 - Alpha
Classifier: Intended Audience :: Education
Classifier: Programming Language :: Python :: 2
Classifier: Programming Language :: Python :: 3
Classifier: Operating System :: MacOS :: MacOS X
Classifier: Operating System :: Microsoft :: Windows
License-File: LICENSE
Requires-Dist: requests
